{
    "global": {
        "check_for_updates_on_startup": true,
        "show_in_menu_bar": true,
        "show_profile_name_in_menu_bar": false
    },
    "profiles": [
        {
            "complex_modifications": {
                "parameters": {
                    "basic.simultaneous_threshold_milliseconds": 50,
                    "basic.to_delayed_action_delay_milliseconds": 500,
                    "basic.to_if_alone_timeout_milliseconds": 1000,
                    "basic.to_if_held_down_threshold_milliseconds": 500,
                    "mouse_motion_to_scroll.speed": 100
                },
                "rules": [
                    {
                        "description": "Change spacebar to left_shift. (Post spacebar if pressed alone)",
                        "manipulators": [
                            {
                                "from": {
                                    "key_code": "spacebar",
                                    "modifiers": {
                                        "optional": [
                                            "any"
                                        ]
                                    }
                                },
                                "to": [
                                    {
                                        "key_code": "left_shift"
                                    }
                                ],
                                "to_if_alone": [
                                    {
                                        "key_code": "spacebar"
                                    }
                                ],
                                "type": "basic"
                            }
                        ]
                    },
                    {
                        "description": "CapsLock to Hyper/Escape",
                        "manipulators": [
                            {
                                "from": {
                                    "key_code": "caps_lock",
                                    "modifiers": {
                                        "optional": [
                                            "any"
                                        ]
                                    }
                                },
                                "to": [
                                    {
                                        "key_code": "right_shift",
                                        "modifiers": [
                                            "right_command",
                                            "right_control",
                                            "right_option"
                                        ]
                                    }
                                ],
                                "to_if_alone": [
                                    {
                                        "key_code": "escape"
                                    }
                                ],
                                "type": "basic"
                            }
                        ]
                    },
                    {
                        "description": "Hyper Application",
                        "manipulators": [
                            {
                                "from": {
                                    "key_code": "v",
                                    "modifiers": {
                                        "mandatory": [
                                            "right_command",
                                            "right_control",
                                            "right_shift",
                                            "right_option"
                                        ]
                                    }
                                },
                                "to": [
                                    {
                                        "shell_command": "open -a 'Visual Studio Code'"
                                    }
                                ],
                                "type": "basic"
                            },
                            {
                                "from": {
                                    "key_code": "t",
                                    "modifiers": {
                                        "mandatory": [
                                            "right_command",
                                            "right_control",
                                            "right_shift",
                                            "right_option"
                                        ]
                                    }
                                },
                                "to": [
                                    {
                                        "shell_command": "open -a 'iterm'"
                                    }
                                ],
                                "type": "basic"
                            },
                            {
                                "from": {
                                    "key_code": "d",
                                    "modifiers": {
                                        "mandatory": [
                                            "right_command",
                                            "right_control",
                                            "right_shift",
                                            "right_option"
                                        ]
                                    }
                                },
                                "to": [
                                    {
                                        "shell_command": "open -a 'IntelliJ IDEA'"
                                    }
                                ],
                                "type": "basic"
                            },
                            {
                                "from": {
                                    "key_code": "g",
                                    "modifiers": {
                                        "mandatory": [
                                            "right_command",
                                            "right_control",
                                            "right_shift",
                                            "right_option"
                                        ]
                                    }
                                },
                                "to": [
                                    {
                                        "shell_command": "open -a 'Google Chrome'"
                                    }
                                ],
                                "type": "basic"
                            },
                            {
                                "from": {
                                    "key_code": "s",
                                    "modifiers": {
                                        "mandatory": [
                                            "right_command",
                                            "right_control",
                                            "right_shift",
                                            "right_option"
                                        ]
                                    }
                                },
                                "to": [
                                    {
                                        "shell_command": "open -a 'Slack'"
                                    }
                                ],
                                "type": "basic"
                            },
                            {
                                "from": {
                                    "key_code": "f",
                                    "modifiers": {
                                        "mandatory": [
                                            "right_command",
                                            "right_control",
                                            "right_shift",
                                            "right_option"
                                        ]
                                    }
                                },
                                "to": [
                                    {
                                        "shell_command": "open -a 'Todoist'"
                                    }
                                ],
                                "type": "basic"
                            },
                            {
                                "from": {
                                    "key_code": "o",
                                    "modifiers": {
                                        "mandatory": [
                                            "right_command",
                                            "right_control",
                                            "right_shift",
                                            "right_option"
                                        ]
                                    }
                                },
                                "to": [
                                    {
                                        "shell_command": "open -a 'Obsidian'"
                                    }
                                ],
                                "type": "basic"
                            },
                            {
                                "from": {
                                    "key_code": "e",
                                    "modifiers": {
                                        "mandatory": [
                                            "right_command",
                                            "right_control",
                                            "right_shift",
                                            "right_option"
                                        ]
                                    }
                                },
                                "to": [
                                    {
                                        "shell_command": "open -a 'Finder'"
                                    }
                                ],
                                "type": "basic"
                            }
                        ]
                    },
                    {
                        "description": "Post escape if left_control is pressed alone.",
                        "manipulators": [
                            {
                                "from": {
                                    "key_code": "left_control",
                                    "modifiers": {
                                        "optional": [
                                            "any"
                                        ]
                                    }
                                },
                                "to": [
                                    {
                                        "key_code": "left_control"
                                    }
                                ],
                                "to_if_alone": [
                                    {
                                        "key_code": "escape"
                                    }
                                ],
                                "type": "basic"
                            }
                        ]
                    },
                    {
                        "description": "コマンドキーを単体で押したときに、英数・かなキーを送信する。（左コマンドキーは英数、右コマンドキーはかな） (rev 3)",
                        "manipulators": [
                            {
                                "from": {
                                    "key_code": "left_command",
                                    "modifiers": {
                                        "optional": [
                                            "any"
                                        ]
                                    }
                                },
                                "parameters": {
                                    "basic.to_if_held_down_threshold_milliseconds": 100
                                },
                                "to": [
                                    {
                                        "key_code": "left_command",
                                        "lazy": true
                                    }
                                ],
                                "to_if_alone": [
                                    {
                                        "key_code": "japanese_eisuu"
                                    }
                                ],
                                "to_if_held_down": [
                                    {
                                        "key_code": "left_command"
                                    }
                                ],
                                "type": "basic"
                            },
                            {
                                "from": {
                                    "key_code": "right_command",
                                    "modifiers": {
                                        "optional": [
                                            "any"
                                        ]
                                    }
                                },
                                "parameters": {
                                    "basic.to_if_held_down_threshold_milliseconds": 100
                                },
                                "to": [
                                    {
                                        "key_code": "right_command",
                                        "lazy": true
                                    }
                                ],
                                "to_if_alone": [
                                    {
                                        "key_code": "japanese_kana"
                                    }
                                ],
                                "to_if_held_down": [
                                    {
                                        "key_code": "right_command"
                                    }
                                ],
                                "type": "basic"
                            }
                        ]
                    },
                    {
                        "description": "Hyper Functional",
                        "manipulators": [
                            {
                                "from": {
                                    "key_code": "f1",
                                    "modifiers": {
                                        "mandatory": [
                                            "right_command",
                                            "right_control",
                                            "right_shift",
                                            "right_option"
                                        ]
                                    }
                                },
                                "to": [
                                    {
                                        "key_code": "display_brightness_decrement"
                                    }
                                ],
                                "type": "basic"
                            },
                            {
                                "from": {
                                    "key_code": "f2",
                                    "modifiers": {
                                        "mandatory": [
                                            "right_command",
                                            "right_control",
                                            "right_shift",
                                            "right_option"
                                        ]
                                    }
                                },
                                "to": [
                                    {
                                        "key_code": "display_brightness_increment"
                                    }
                                ],
                                "type": "basic"
                            },
                            {
                                "from": {
                                    "key_code": "f3",
                                    "modifiers": {
                                        "mandatory": [
                                            "right_command",
                                            "right_control",
                                            "right_shift",
                                            "right_option"
                                        ]
                                    }
                                },
                                "to": [
                                    {
                                        "key_code": "up_arrow",
                                        "modifiers": [
                                            "left_control"
                                        ]
                                    }
                                ],
                                "type": "basic"
                            },
                            {
                                "from": {
                                    "key_code": "f4",
                                    "modifiers": {
                                        "mandatory": [
                                            "right_command",
                                            "right_control",
                                            "right_shift",
                                            "right_option"
                                        ]
                                    }
                                },
                                "to": [
                                    {
                                        "shell_command": "open -a 'Launchpad'"
                                    }
                                ],
                                "type": "basic"
                            },
                            {
                                "from": {
                                    "key_code": "f5",
                                    "modifiers": {
                                        "mandatory": [
                                            "right_command",
                                            "right_control",
                                            "right_shift",
                                            "right_option"
                                        ]
                                    }
                                },
                                "to": [
                                    {
                                        "key_code": "illumination_decrement"
                                    }
                                ],
                                "type": "basic"
                            },
                            {
                                "from": {
                                    "key_code": "f6",
                                    "modifiers": {
                                        "mandatory": [
                                            "right_command",
                                            "right_control",
                                            "right_shift",
                                            "right_option"
                                        ]
                                    }
                                },
                                "to": [
                                    {
                                        "key_code": "illumination_increment"
                                    }
                                ],
                                "type": "basic"
                            },
                            {
                                "from": {
                                    "key_code": "f7",
                                    "modifiers": {
                                        "mandatory": [
                                            "right_command",
                                            "right_control",
                                            "right_shift",
                                            "right_option"
                                        ]
                                    }
                                },
                                "to": [
                                    {
                                        "key_code": "rewind"
                                    }
                                ],
                                "type": "basic"
                            },
                            {
                                "from": {
                                    "key_code": "f8",
                                    "modifiers": {
                                        "mandatory": [
                                            "right_command",
                                            "right_control",
                                            "right_shift",
                                            "right_option"
                                        ]
                                    }
                                },
                                "to": [
                                    {
                                        "key_code": "play_or_pause"
                                    }
                                ],
                                "type": "basic"
                            },
                            {
                                "from": {
                                    "key_code": "f9",
                                    "modifiers": {
                                        "mandatory": [
                                            "right_command",
                                            "right_control",
                                            "right_shift",
                                            "right_option"
                                        ]
                                    }
                                },
                                "to": [
                                    {
                                        "key_code": "fastforward"
                                    }
                                ],
                                "type": "basic"
                            },
                            {
                                "from": {
                                    "key_code": "f10",
                                    "modifiers": {
                                        "mandatory": [
                                            "right_command",
                                            "right_control",
                                            "right_shift",
                                            "right_option"
                                        ]
                                    }
                                },
                                "to": [
                                    {
                                        "key_code": "mute"
                                    }
                                ],
                                "type": "basic"
                            },
                            {
                                "from": {
                                    "key_code": "f11",
                                    "modifiers": {
                                        "mandatory": [
                                            "right_command",
                                            "right_control",
                                            "right_shift",
                                            "right_option"
                                        ]
                                    }
                                },
                                "to": [
                                    {
                                        "key_code": "volume_decrement"
                                    }
                                ],
                                "type": "basic"
                            },
                            {
                                "from": {
                                    "key_code": "f12",
                                    "modifiers": {
                                        "mandatory": [
                                            "right_command",
                                            "right_control",
                                            "right_shift",
                                            "right_option"
                                        ]
                                    }
                                },
                                "to": [
                                    {
                                        "key_code": "volume_increment"
                                    }
                                ],
                                "type": "basic"
                            },
                            {
                                "from": {
                                    "key_code": "f13",
                                    "modifiers": {
                                        "mandatory": [
                                            "right_command",
                                            "right_control",
                                            "right_shift",
                                            "right_option"
                                        ]
                                    }
                                },
                                "to": [
                                    {
                                        "key_code": "rewind"
                                    }
                                ],
                                "type": "basic"
                            },
                            {
                                "from": {
                                    "key_code": "f14",
                                    "modifiers": {
                                        "mandatory": [
                                            "right_command",
                                            "right_control",
                                            "right_shift",
                                            "right_option"
                                        ]
                                    }
                                },
                                "to": [
                                    {
                                        "key_code": "fastforward"
                                    }
                                ],
                                "type": "basic"
                            },
                            {
                                "from": {
                                    "key_code": "f15",
                                    "modifiers": {
                                        "mandatory": [
                                            "right_command",
                                            "right_control",
                                            "right_shift",
                                            "right_option"
                                        ]
                                    }
                                },
                                "to": [
                                    {
                                        "key_code": "mute"
                                    }
                                ],
                                "type": "basic"
                            },
                            {
                                "from": {
                                    "key_code": "insert",
                                    "modifiers": {
                                        "mandatory": [
                                            "right_command",
                                            "right_control",
                                            "right_shift",
                                            "right_option"
                                        ]
                                    }
                                },
                                "to": [
                                    {
                                        "key_code": "display_brightness_increment",
                                        "modifiers": [
                                            "left_shift",
                                            "left_option"
                                        ]
                                    }
                                ],
                                "type": "basic"
                            },
                            {
                                "from": {
                                    "key_code": "delete_forward",
                                    "modifiers": {
                                        "mandatory": [
                                            "right_command",
                                            "right_control",
                                            "right_shift",
                                            "right_option"
                                        ]
                                    }
                                },
                                "to": [
                                    {
                                        "key_code": "display_brightness_decrement",
                                        "modifiers": [
                                            "left_shift",
                                            "left_option"
                                        ]
                                    }
                                ],
                                "type": "basic"
                            },
                            {
                                "from": {
                                    "key_code": "home",
                                    "modifiers": {
                                        "mandatory": [
                                            "right_command",
                                            "right_control",
                                            "right_shift",
                                            "right_option"
                                        ]
                                    }
                                },
                                "to": [
                                    {
                                        "key_code": "illumination_increment",
                                        "modifiers": [
                                            "left_shift",
                                            "left_option"
                                        ]
                                    }
                                ],
                                "type": "basic"
                            },
                            {
                                "from": {
                                    "key_code": "end",
                                    "modifiers": {
                                        "mandatory": [
                                            "right_command",
                                            "right_control",
                                            "right_shift",
                                            "right_option"
                                        ]
                                    }
                                },
                                "to": [
                                    {
                                        "key_code": "illumination_decrement",
                                        "modifiers": [
                                            "left_shift",
                                            "left_option"
                                        ]
                                    }
                                ],
                                "type": "basic"
                            },
                            {
                                "from": {
                                    "key_code": "page_down",
                                    "modifiers": {
                                        "mandatory": [
                                            "right_command",
                                            "right_control",
                                            "right_shift",
                                            "right_option"
                                        ]
                                    }
                                },
                                "to": [
                                    {
                                        "key_code": "volume_decrement"
                                    }
                                ],
                                "type": "basic"
                            },
                            {
                                "from": {
                                    "key_code": "page_up",
                                    "modifiers": {
                                        "mandatory": [
                                            "right_command",
                                            "right_control",
                                            "right_shift",
                                            "right_option"
                                        ]
                                    }
                                },
                                "to": [
                                    {
                                        "key_code": "volume_increment"
                                    }
                                ],
                                "type": "basic"
                            }
                        ]
                    },
                    {
                        "description": "Quit application by holding command-q",
                        "manipulators": [
                            {
                                "from": {
                                    "key_code": "q",
                                    "modifiers": {
                                        "mandatory": [
                                            "command"
                                        ],
                                        "optional": [
                                            "caps_lock"
                                        ]
                                    }
                                },
                                "to_if_held_down": [
                                    {
                                        "key_code": "q",
                                        "modifiers": [
                                            "left_command"
                                        ],
                                        "repeat": false
                                    }
                                ],
                                "type": "basic"
                            }
                        ]
                    }
                ]
            },
            "devices": [
                {
                    "disable_built_in_keyboard_if_exists": true,
                    "fn_function_keys": [],
                    "identifiers": {
                        "is_keyboard": true,
                        "is_pointing_device": true,
                        "product_id": 626,
                        "vendor_id": 1241
                    },
                    "ignore": true,
                    "manipulate_caps_lock_led": false,
                    "simple_modifications": []
                }
            ],
            "fn_function_keys": [
                {
                    "from": {
                        "key_code": "f1"
                    },
                    "to": [
                        {
                            "consumer_key_code": "display_brightness_decrement"
                        }
                    ]
                },
                {
                    "from": {
                        "key_code": "f2"
                    },
                    "to": [
                        {
                            "consumer_key_code": "display_brightness_increment"
                        }
                    ]
                },
                {
                    "from": {
                        "key_code": "f3"
                    },
                    "to": [
                        {
                            "key_code": "mission_control"
                        }
                    ]
                },
                {
                    "from": {
                        "key_code": "f4"
                    },
                    "to": [
                        {
                            "key_code": "launchpad"
                        }
                    ]
                },
                {
                    "from": {
                        "key_code": "f5"
                    },
                    "to": [
                        {
                            "key_code": "illumination_decrement"
                        }
                    ]
                },
                {
                    "from": {
                        "key_code": "f6"
                    },
                    "to": [
                        {
                            "key_code": "illumination_increment"
                        }
                    ]
                },
                {
                    "from": {
                        "key_code": "f7"
                    },
                    "to": [
                        {
                            "consumer_key_code": "rewind"
                        }
                    ]
                },
                {
                    "from": {
                        "key_code": "f8"
                    },
                    "to": [
                        {
                            "consumer_key_code": "play_or_pause"
                        }
                    ]
                },
                {
                    "from": {
                        "key_code": "f9"
                    },
                    "to": [
                        {
                            "consumer_key_code": "fastforward"
                        }
                    ]
                },
                {
                    "from": {
                        "key_code": "f10"
                    },
                    "to": [
                        {
                            "consumer_key_code": "mute"
                        }
                    ]
                },
                {
                    "from": {
                        "key_code": "f11"
                    },
                    "to": [
                        {
                            "consumer_key_code": "volume_decrement"
                        }
                    ]
                },
                {
                    "from": {
                        "key_code": "f12"
                    },
                    "to": [
                        {
                            "consumer_key_code": "volume_increment"
                        }
                    ]
                }
            ],
            "name": "Default profile",
            "parameters": {
                "delay_milliseconds_before_open_device": 1000
            },
            "selected": true,
            "simple_modifications": [
                {
                    "from": {
                        "key_code": "escape"
                    },
                    "to": [
                        {
                            "key_code": "grave_accent_and_tilde"
                        }
                    ]
                },
                {
                    "from": {
                        "key_code": "right_alt"
                    },
                    "to": [
                        {
                            "key_code": "right_command"
                        }
                    ]
                }
            ],
            "virtual_hid_keyboard": {
                "country_code": 45,
                "indicate_sticky_modifier_keys_state": true,
                "mouse_key_xy_scale": 100
            }
        }
    ]
}
